rlcms/__init__.py
rlcms/composites.py
rlcms/covariates.py
rlcms/harmonics.py
rlcms/primitives.py
rlcms/sampling.py
rlcms/utils.py
rlcms/cli/composite.py
rlcms/cli/landcover.py
rlcms/cli/primitives.py
rlcms/cli/sample_pts.py
rlcms/cli/train_test.py
rlcms-2024.7.2.dist-info/LICENSE
rlcms-2024.7.2.dist-info/METADATA
rlcms-2024.7.2.dist-info/WHEEL
rlcms-2024.7.2.dist-info/entry_points.txt
rlcms-2024.7.2.dist-info/top_level.txt
rlcms-2024.7.2.dist-info/RECORD
