Metadata-Version: 2.1
Name: rlcms
Version: 2024.7.2
Summary: workflows for regional land cover mapping, built in Google Earth Engine
Author-email: Kyle Woodward <kw.geospatial@gmail.com>
License: GNU GENERAL PUBLIC LICENSE
Project-URL: Homepage, https://github.com/sig-gis/rlcms/
Keywords: land cover,mapping
Classifier: Programming Language :: Python
Classifier: Programming Language :: Python :: 3
Requires-Python: >=3.8
License-File: LICENSE
Requires-Dist: earthengine-api
Requires-Dist: hydrafloods
Requires-Dist: pandas
Provides-Extra: dev
Requires-Dist: geemap ; extra == 'dev'
